MANIFEST.in
setup.py
bin/setup_pipe
bin/wrap
cloud_pipe/__init__.py
cloud_pipe/utils.py
cloud_pipe.egg-info/PKG-INFO
cloud_pipe.egg-info/SOURCES.txt
cloud_pipe.egg-info/dependency_links.txt
cloud_pipe.egg-info/entry_points.txt
cloud_pipe.egg-info/not-zip-safe
cloud_pipe.egg-info/requires.txt
cloud_pipe.egg-info/top_level.txt
cloud_pipe/algorithms/change123-s3_info.json
cloud_pipe/pipeline/__init__.py
cloud_pipe/pipeline/cleanup.py
cloud_pipe/pipeline/config.py
cloud_pipe/pipeline/image_class.py
cloud_pipe/pipeline/set_pipe.py
cloud_pipe/pipeline/task_config.py
cloud_pipe/templates/ecs_task_definition_template.txt
cloud_pipe/templates/lambda_exec_role.txt
cloud_pipe/templates/lambda_run_task_template.txt
cloud_pipe/templates/runscript_template.txt
cloud_pipe/templates/scatter_all.txt
cloud_pipe/templates/ubuntu_wrapper.txt
cloud_pipe/wrapper/__init__.py
cloud_pipe/wrapper/container_wrapper.py